pi_controller/__init__.py
pi_controller/main.py
pi_controller-1.0.0.dist-info/LICENSE.txt
pi_controller-1.0.0.dist-info/METADATA
pi_controller-1.0.0.dist-info/WHEEL
pi_controller-1.0.0.dist-info/top_level.txt
pi_controller-1.0.0.dist-info/RECORD
