Metadata-Version: 2.2
Name: pi_controller
Version: 1.0.0
Summary: A library for nintendo switch pro controller support with raspberry pi.
Author: PreciousFood
Project-URL: Homepage, https://github.com/PreciousFood/pi_controller
Keywords: pi,raspberry pi,controller,pro controller
Classifier: Development Status :: 5 - Production/Stable
Classifier: Intended Audience :: Developers
Classifier: License :: OSI Approved :: MIT License
Classifier: Programming Language :: Python :: 3
Requires-Python: >=3.8
License-File: LICENSE.txt
Requires-Dist: evdev
